[{"id":194601,"createdDate":"2021-01-16T19:25:14.900Z","updatedDate":"2021-01-16T20:42:34.487Z","startTime":"15:20:00","startDate":"2021-02-20","totalAppointments":30,"activeAppointments":18,"bookedAppointments":18,"availableAppointments":12},{"id":194609,"createdDate":"2021-01-16T19:25:14.900Z","updatedDate":"2021-01-16T20:42:34.517Z","startTime":"16:40:00","startDate":"2021-02-20","totalAppointments":30,"activeAppointments":21,"bookedAppointments":21,"availableAppointments":9},{"id":194610,"createdDate":"2021-01-16T19:25:14.900Z","updatedDate":"2021-01-16T20:42:34.520Z","startTime":"16:50:00","startDate":"2021-02-20","totalAppointments":30,"activeAppointments":25,"bookedAppointments":25,"availableAppointments":5},{"id":194600,"createdDate":"2021-01-16T19:25:14.900Z","updatedDate":"2021-01-16T20:42:34.483Z","startTime":"15:10:00","startDate":"2021-02-20","totalAppointments":30,"activeAppointments":25,"bookedAppointments":25,"availableAppointments":5},{"id":194604,"createdDate":"2021-01-16T19:25:14.900Z","updatedDate":"2021-01-16T20:42:34.499Z","startTime":"15:50:00","startDate":"2021-02-20","totalAppointments":30,"activeAppointments":21,"bookedAppointments":21,"availableAppointments":9},{"id":194605,"createdDate":"2021-01-16T19:25:14.900Z","updatedDate":"2021-01-16T20:42:34.503Z","startTime":"16:00:00","startDate":"2021-02-20","totalAppointments":30,"activeAppointments":24,"bookedAppointments":24,"availableAppointments":6},{"id":194607,"createdDate":"2021-01-16T19:25:14.900Z","updatedDate":"2021-01-16T20:42:34.511Z","startTime":"16:20:00","startDate":"2021-02-20","totalAppointments":30,"activeAppointments":24,"bookedAppointments":24,"availableAppointments":6},{"id":194608,"createdDate":"2021-01-16T19:25:14.900Z","updatedDate":"2021-01-16T20:42:34.514Z","startTime":"16:30:00","startDate":"2021-02-20","totalAppointments":30,"activeAppointments":24,"bookedAppointments":24,"availableAppointments":6},{"id":194603,"createdDate":"2021-01-16T19:25:14.900Z","updatedDate":"2021-01-16T20:42:34.496Z","startTime":"15:40:00","startDate":"2021-02-20","totalAppointments":30,"activeAppointments":21,"bookedAppointments":21,"availableAppointments":9},{"id":194602,"createdDate":"2021-01-16T19:25:14.900Z","updatedDate":"2021-01-16T20:42:34.492Z","startTime":"15:30:00","startDate":"2021-02-20","totalAppointments":30,"activeAppointments":26,"bookedAppointments":26,"availableAppointments":4},{"id":194606,"createdDate":"2021-01-16T19:25:14.900Z","updatedDate":"2021-01-16T20:42:34.506Z","startTime":"16:10:00","startDate":"2021-02-20","totalAppointments":30,"activeAppointments":22,"bookedAppointments":22,"availableAppointments":8},{"id":194592,"createdDate":"2021-01-16T19:25:14.900Z","updatedDate":"2021-01-16T20:42:34.444Z","startTime":"13:50:00","startDate":"2021-02-20","totalAppointments":30,"activeAppointments":26,"bookedAppointments":26,"availableAppointments":4},{"id":194591,"createdDate":"2021-01-16T19:25:14.900Z","updatedDate":"2021-01-16T20:42:34.441Z","startTime":"13:40:00","startDate":"2021-02-20","totalAppointments":30,"activeAppointments":28,"bookedAppointments":28,"availableAppointments":2},{"id":194585,"createdDate":"2021-01-16T19:25:14.900Z","updatedDate":"2021-01-16T20:42:34.422Z","startTime":"12:40:00","startDate":"2021-02-20","totalAppointments":30,"activeAppointments":29,"bookedAppointments":29,"availableAppointments":1},{"id":194596,"createdDate":"2021-01-16T19:25:14.900Z","updatedDate":"2021-01-16T20:42:34.457Z","startTime":"14:30:00","startDate":"2021-02-20","totalAppointments":30,"activeAppointments":24,"bookedAppointments":24,"availableAppointments":6},{"id":194599,"createdDate":"2021-01-16T19:25:14.900Z","updatedDate":"2021-01-16T20:42:34.468Z","startTime":"15:00:00","startDate":"2021-02-20","totalAppointments":30,"activeAppointments":27,"bookedAppointments":27,"availableAppointments":3},{"id":194595,"createdDate":"2021-01-16T19:25:14.900Z","updatedDate":"2021-01-16T20:42:34.454Z","startTime":"14:20:00","startDate":"2021-02-20","totalAppointments":30,"activeAppointments":29,"bookedAppointments":29,"availableAppointments":1},{"id":194598,"createdDate":"2021-01-16T19:25:14.900Z","updatedDate":"2021-01-16T20:42:34.465Z","startTime":"14:50:00","startDate":"2021-02-20","totalAppointments":30,"activeAppointments":26,"bookedAppointments":26,"availableAppointments":4},{"id":194584,"createdDate":"2021-01-16T19:25:14.900Z","updatedDate":"2021-01-16T20:42:34.418Z","startTime":"12:30:00","startDate":"2021-02-20","totalAppointments":30,"activeAppointments":29,"bookedAppointments":29,"availableAppointments":1},{"id":194593,"createdDate":"2021-01-16T19:25:14.900Z","updatedDate":"2021-01-16T20:42:34.448Z","startTime":"14:00:00","startDate":"2021-02-20","totalAppointments":30,"activeAppointments":27,"bookedAppointments":27,"availableAppointments":3},{"id":194597,"createdDate":"2021-01-16T19:25:14.900Z","updatedDate":"2021-01-16T20:42:34.462Z","startTime":"14:40:00","startDate":"2021-02-20","totalAppointments":30,"activeAppointments":29,"bookedAppointments":29,"availableAppointments":1},{"id":194594,"createdDate":"2021-01-16T19:25:14.900Z","updatedDate":"2021-01-16T20:42:34.451Z","startTime":"14:10:00","startDate":"2021-02-20","totalAppointments":30,"activeAppointments":28,"bookedAppointments":28,"availableAppointments":2},{"id":194582,"createdDate":"2021-01-16T19:25:14.900Z","updatedDate":"2021-01-16T20:42:34.412Z","startTime":"12:10:00","startDate":"2021-02-20","totalAppointments":30,"activeAppointments":29,"bookedAppointments":29,"availableAppointments":1},{"id":194583,"createdDate":"2021-01-16T19:25:14.900Z","updatedDate":"2021-01-16T20:42:34.415Z","startTime":"12:20:00","startDate":"2021-02-20","totalAppointments":30,"activeAppointments":29,"bookedAppointments":29,"availableAppointments":1},{"id":194586,"createdDate":"2021-01-16T19:25:14.900Z","updatedDate":"2021-01-16T20:42:34.425Z","startTime":"12:50:00","startDate":"2021-02-20","totalAppointments":30,"activeAppointments":27,"bookedAppointments":27,"availableAppointments":3}]