[{"id":213363,"createdDate":"2021-01-16T19:56:54.968Z","updatedDate":"2021-01-26T20:56:08.701Z","startTime":"15:20:00","startDate":"2021-02-18","totalAppointments":30,"activeAppointments":5,"bookedAppointments":5,"availableAppointments":25},{"id":213362,"createdDate":"2021-01-16T19:56:54.968Z","updatedDate":"2021-01-26T20:56:08.698Z","startTime":"15:10:00","startDate":"2021-02-18","totalAppointments":30,"activeAppointments":17,"bookedAppointments":17,"availableAppointments":13},{"id":213364,"createdDate":"2021-01-16T19:56:54.968Z","updatedDate":"2021-01-26T20:56:08.704Z","startTime":"15:30:00","startDate":"2021-02-18","totalAppointments":30,"activeAppointments":18,"bookedAppointments":18,"availableAppointments":12},{"id":213360,"createdDate":"2021-01-16T19:56:54.968Z","updatedDate":"2021-01-26T20:56:08.692Z","startTime":"14:50:00","startDate":"2021-02-18","totalAppointments":30,"activeAppointments":25,"bookedAppointments":25,"availableAppointments":5}]